setup.py
setup_math_utils.py
setup_plotting_utils.py
setup_table_utils.py
src/survey_utils.egg-info/PKG-INFO
src/survey_utils.egg-info/SOURCES.txt
src/survey_utils.egg-info/dependency_links.txt
src/survey_utils.egg-info/top_level.txt