Metadata-Version: 1.0
Name: survey-utils
Version: 0.0.5
Summary: Utilities for plotting survey and other results.
Home-page: https://github.com/paepcke/survey_utils
Author: Andreas Paepcke
Author-email: paepcke@cs.stanford.edu
License: BSD
Keywords: surveys,dendrogram,clustering
Platform: UNKNOWN
